strucscan/__init__.py
strucscan/_version.py
strucscan/cli.py
strucscan/scheduler.py
strucscan/utils.py
strucscan/core/__init__.py
strucscan/core/collector.py
strucscan/core/datatree.py
strucscan/core/jobmaker.py
strucscan/core/jobmanager.py
strucscan/core/jobobject.py
strucscan/core/statusmanager.py
strucscan/engine/__init__.py
strucscan/engine/dummy.py
strucscan/engine/generalengine.py
strucscan/engine/vasp.py
strucscan/error/__init__.py
strucscan/error/errorhandler.py
strucscan/error/errormanager.py
strucscan/properties/__init__.py
strucscan/properties/bulk.py
strucscan/properties/eos.py
strucscan/resources/__init__.py
strucscan/resources/atomicdata.py
strucscan/resources/inputyaml.py
strucscan/resources/properties.py
strucscan/resources/properties.yaml
strucscan-0.post0.dev68.dist-info/LICENSE
strucscan-0.post0.dev68.dist-info/METADATA
strucscan-0.post0.dev68.dist-info/WHEEL
strucscan-0.post0.dev68.dist-info/entry_points.txt
strucscan-0.post0.dev68.dist-info/top_level.txt
strucscan-0.post0.dev68.dist-info/RECORD
